j5test/ArrayDim.py
j5test/BrowserDim.py
j5test/DictDim.py
j5test/IterativeTester.py
j5test/LoggingTest.py
j5test/NoseRunner.py
j5test/NoseTests.py
j5test/SampleNoseTests.py
j5test/SampleNoseTestsFailure.py
j5test/ThreadWeave.py
j5test/Utils.py
j5test/__init__.py
j5test/test_Dims.py
j5test/test_IterativeTester.py
j5test/test_LoggingTest.py
j5test/test_NoseTests.py
j5test/test_ThreadWeave.py
j5test/test_Utils.py
j5test-1.3.dist-info/LICENSE
j5test-1.3.dist-info/METADATA
j5test-1.3.dist-info/WHEEL
j5test-1.3.dist-info/pbr.json
j5test-1.3.dist-info/top_level.txt
j5test-1.3.dist-info/RECORD
